DurgaMusicAPI/__init__.py
DurgaMusicAPI-0.0.2.dist-info/LICENSE
DurgaMusicAPI-0.0.2.dist-info/METADATA
DurgaMusicAPI-0.0.2.dist-info/WHEEL
DurgaMusicAPI-0.0.2.dist-info/top_level.txt
DurgaMusicAPI-0.0.2.dist-info/RECORD
